ECOv003_exit_codes/ECOv003_exit_codes.py
ECOv003_exit_codes/__init__.py
ECOv003_exit_codes/version.txt
ecov003_exit_codes-1.1.0.dist-info/licenses/LICENSE
ecov003_exit_codes-1.1.0.dist-info/METADATA
ecov003_exit_codes-1.1.0.dist-info/WHEEL
ecov003_exit_codes-1.1.0.dist-info/top_level.txt
ecov003_exit_codes-1.1.0.dist-info/RECORD
